error_explainer_cl/__init__.py
error_explainer_cl/cli.py
error_explainer_cl/knowledge_base.json
error_explainer_cl/resolver.py
error_explainer_cl-0.1.0.dist-info/entry_points.txt
error_explainer_cl-0.1.0.dist-info/licenses/LICENSE
error_explainer_cl-0.1.0.dist-info/WHEEL
error_explainer_cl-0.1.0.dist-info/METADATA
error_explainer_cl-0.1.0.dist-info/RECORD
