Metadata-Version: 2.4
Name: error_explainer_cl
Version: 0.1.0
Summary: 🐍 A CLI tool to explain Python errors in plain English.
Author-email: Ejike Anazor <ejikeanaz66@gmail.com>
License-File: LICENSE
